MANIFEST.in
README.txt
setup.py
collective/__init__.py
collective.seo.egg-info/PKG-INFO
collective.seo.egg-info/SOURCES.txt
collective.seo.egg-info/dependency_links.txt
collective.seo.egg-info/entry_points.txt
collective.seo.egg-info/namespace_packages.txt
collective.seo.egg-info/not-zip-safe
collective.seo.egg-info/requires.txt
collective.seo.egg-info/top_level.txt
collective/seo/__init__.py
collective/seo/configure.zcml
collective/seo/interfaces.py
collective/seo/storage.py
collective/seo/tests.py
collective/seo/browser/__init__.py
collective/seo/browser/configure.zcml
collective/seo/browser/keywords.py
collective/seo/browser/settings.py
collective/seo/browser/title.py
collective/seo/profiles/default/actions.xml
collective/seo/profiles/default/browserlayer.xml
collective/seo/profiles/default/metadata.xml
docs/HISTORY.txt
docs/INSTALL.txt
docs/LICENSE.txt