Metadata-Version: 1.0
Name: collective.seo
Version: 1.1
Summary: SEO add-on let you set values of some html header tags.
Home-page: https://github.com/collective/collective.seo
Author: JeanMichel FRANCOIS aka toutpt
Author-email: toutpt@gmail.com
License: GPL
Platform: UNKNOWN
Classifier: Framework :: Plone
Classifier: Programming Language :: Python
